diamond_square/__init__.py
diamond_square/diamond_square.py
tormentor/__init__.py
tormentor/augmented_dataset.py
tormentor/backgrounds.py
tormentor/base_augmentation.py
tormentor/color_augmentations.py
tormentor/layer.py
tormentor/random.py
tormentor/render_sampling_field.py
tormentor/spatial_augmentations.py
tormentor/text_render.py
tormentor/util.py
tormentor/wrap.py
tormentor-0.1.0.dist-info/LICENSE
tormentor-0.1.0.dist-info/METADATA
tormentor-0.1.0.dist-info/WHEEL
tormentor-0.1.0.dist-info/top_level.txt
tormentor-0.1.0.dist-info/RECORD
