Metadata-Version: 2.1
Name: tormentor
Version: 0.1.0
Summary: A very easy to use argument parser.
Home-page: https://github.com/anguelos/tormentor
Author: Anguelos Nicolaou
Author-email: anguelos.nicolaou@gmail.com
License: MIT
Download-URL: https://github.com/anguelos/tormentor/archive/0.1.0.tar.gz
Keywords: pytorch,augmentation,kornia,image segmentation,computer vision
Platform: UNKNOWN
Classifier: Intended Audience :: Science/Research
Classifier: Programming Language :: Python :: 3.6
Classifier: Programming Language :: Python :: 3.7
Classifier: Programming Language :: Python :: 3.8
Classifier: Topic :: Scientific/Engineering
Requires-Dist: torch
Requires-Dist: matplotlib
Requires-Dist: torchvision
Requires-Dist: fargv
